taitale/__init__.py
taitale/askap/__init__.py
taitale/askap/cbpcalibrator.py
taitale/askap/ccalapply.py
taitale/askap/ccalibrator.py
taitale/askap/ccontsubtract.py
taitale/askap/cddcalibrator.py
taitale/askap/cmodel.py
taitale/askap/csimulator.py
taitale/askap/imager.py
taitale/askap/imcontsub.py
taitale/askap/linmos.py
taitale/askap/msconcat.py
taitale/askap/mslist.py
taitale/askap/msmerge.py
taitale/askap/mssplit.py
taitale/askap/selavy.py
taitale/env.py
taitale/taitale_env.cfg
taitale/tools/__init__.py
taitale/tools/dp3.py
taitale/tools/losoto.py
taitale/tools/wsclean.py
taitale/utils/CliArgs.py
taitale/utils/Parset.py
taitale/utils/__init__.py
taitale/utils/argumentset.py
taitale/utils/wrapper.py
taitale/widgets/ICmdRunWithLogTrail.py
taitale/widgets/__init__.py
taitale-1.1.0.dist-info/LICENSE
taitale-1.1.0.dist-info/METADATA
taitale-1.1.0.dist-info/WHEEL
taitale-1.1.0.dist-info/RECORD
