Metadata-Version: 2.1
Name: taitale
Version: 1.1.0
Summary: taitale a tool to utilize and craft pipelines with ASKAPsoft and other radio astronomy tools
License: GNU GPLv3
Keywords: astronomy
Author: M.Nimalan
Author-email: nimalan.m@protonmail.com
Requires-Python: >=3.10
Classifier: Development Status :: 4 - Beta
Classifier: Intended Audience :: Science/Research
Classifier: License :: OSI Approved :: GNU General Public License v3 or later (GPLv3+)
Classifier: License :: Other/Proprietary License
Classifier: Programming Language :: Python
Classifier: Programming Language :: Python :: 3
Classifier: Programming Language :: Python :: 3.10
Classifier: Programming Language :: Python :: 3.11
Classifier: Programming Language :: Python :: 3.12
